pytexit/__init__.py
pytexit/__version__.txt
pytexit/pytexit.py
pytexit/core/__init__.py
pytexit/core/core.py
pytexit/core/docx.py
pytexit/core/fortran.py
pytexit/test/__init__.py
pytexit/test/test_docx.py
pytexit/test/test_fortran.py
pytexit/test/test_functions.py
pytexit-0.4.0.data/scripts/py2tex
pytexit-0.4.0.dist-info/LICENSE
pytexit-0.4.0.dist-info/METADATA
pytexit-0.4.0.dist-info/WHEEL
pytexit-0.4.0.dist-info/top_level.txt
pytexit-0.4.0.dist-info/RECORD
