Metadata-Version: 2.1
Name: pytexit
Version: 0.4.0
Summary: Convert a Python expression to a LaTeX formula
Home-page: http://pytexit.readthedocs.io/
Author: Erwan Pannier
Author-email: erwan.pannier@gmail.com
License: CeCILL-2.1
Keywords: latex,py2tex
Platform: any
Classifier: Development Status :: 4 - Beta
Classifier: Intended Audience :: Science/Research
Classifier: License :: OSI Approved :: CEA CNRS Inria Logiciel Libre License, version 2.1 (CeCILL-2.1)
Classifier: Topic :: Scientific/Engineering
Classifier: Topic :: Text Processing
Classifier: Programming Language :: Python
Classifier: Programming Language :: Python :: 2.7
Classifier: Programming Language :: Python :: 3.4
Classifier: Programming Language :: Python :: 3.5
Classifier: Programming Language :: Python :: 3.6
Classifier: Programming Language :: Python :: 3.8
Classifier: Programming Language :: Python :: 3.9
Classifier: Operating System :: OS Independent
License-File: LICENSE
Requires-Dist: six
